aclpubcheck/__init__.py
aclpubcheck/copyright_signatures.py
aclpubcheck/formatchecker.py
aclpubcheck/googletools.py
aclpubcheck/metadatachecker.py
aclpubcheck/name_check.py
aclpubcheck-0.2.0.dist-info/entry_points.txt
aclpubcheck-0.2.0.dist-info/LICENSE
aclpubcheck-0.2.0.dist-info/WHEEL
aclpubcheck-0.2.0.dist-info/METADATA
aclpubcheck-0.2.0.dist-info/RECORD
