Metadata-Version: 2.1
Name: aclpubcheck
Version: 0.2.0
Summary: 
License: MIT
Author: Yichao Zhou
Requires-Python: >=3.8,<4.0
Classifier: License :: OSI Approved :: MIT License
Classifier: Programming Language :: Python :: 3
Classifier: Programming Language :: Python :: 3.8
Classifier: Programming Language :: Python :: 3.9
Classifier: Programming Language :: Python :: 3.10
Requires-Dist: Unidecode (>=1.3.6,<2.0.0)
Requires-Dist: pandas (>=1.5.0,<2.0.0)
Requires-Dist: pdfplumber (>=0.7.5,<0.8.0)
Requires-Dist: pybtex (>=0.24.0,<0.25.0)
Requires-Dist: pylatexenc (>=2.10,<3.0)
Requires-Dist: rebiber (>=1.1.3,<2.0.0)
Requires-Dist: termcolor (>=2.0.1,<3.0.0)
Requires-Dist: tqdm (>=4.64.1,<5.0.0)
Requires-Dist: tsv (>=1.2,<2.0)
